hquery/__init__.py
hquery/cli.py
hquery/compiler.py
hquery-1.0.0.dist-info/METADATA
hquery-1.0.0.dist-info/WHEEL
hquery-1.0.0.dist-info/entry_points.txt
hquery-1.0.0.dist-info/top_level.txt
hquery-1.0.0.dist-info/RECORD
