Metadata-Version: 2.4
Name: hquery
Version: 1.0.0
Summary: HTML DSL Language
Author-email: Sarthak Ghoshal <sarthak22.ghoshal@gmail.com>
Requires-Python: >=3.8
Requires-Dist: typer[all]
Requires-Dist: colorama
